rtl/bu/barret_reduction/barrett_reduction.sv
`timescale 1ps/1ps

module barrett_reduction (
    input [31:0] c,       // 32-bit number to be reduced
    output [15:0] result  // Result of c mod q
);
    // Define q and mu as parameters
    parameter q = 16'hD01; // 3329 in hex
    //parameter k = 32;       // Bit length for reduction
    parameter mu = 32'h13AFB7; // Precomputed value of floor(2^k / q)

    // Compute c * mu
   /* verilator lint_off UNUSEDSIGNAL */
   wire [63:0] c_mu;

    assign c_mu = c * mu;

    wire [31:0] c_mu_l;

    assign c_mu_l = c_mu[63:32];

    // Compute floor(c_mu / 2^k) * q
    wire [31:0] floor_c_mu_q;

    assign floor_c_mu_q = c_mu_l * q;

wire [15:0] result_temp;
    // Compute c - floor_c_mu_q
/* verilator lint_off WIDTHTRUNC */
    assign result_temp = c - floor_c_mu_q;
/* verilator lint_off WIDTHTRUNC */

assign result = (result_temp >= q)? result_temp - q : result_temp;

endmodule

rtl/bu/tb_barrett_reduction.sv
`timescale 1ps/1ps
`include "barrett_reduction.sv"

module tb_barrett_reduction;
    reg [31:0] c; // Input
    wire [15:0] result; // Output
    
    reg [31:0] expected_result;

    // Instantiate the barrett_reduction module
    barrett_reduction uut (
        .c(c),
        .result(result)
    );

    // File handles for writing to the text files
    integer input_file, output_file;

    initial begin
        // Open the text files
        input_file = $fopen("input.txt", "w");
        output_file = $fopen("output.txt", "w");

        // Test with 1000 random 32-bit inputs
        for (integer i = 0; i < 1000; i = i + 1) begin
            // Generate a random 32-bit input
            c = $random;

            // Write the input to the input.txt file
            $fwrite(input_file, "%h\n", c);
            #10;
            // Wait for the uut to process the input

            // Compute the expected output
            expected_result = c % 3329;

            // Write the output and the expected output to the output.txt file
            $fwrite(output_file, "%h %h\n", result, expected_result);
        end

        // Close the text files
        $fclose(input_file);
        $fclose(output_file);
        #3000
        // Finish the simulation
        $finish;
    end

    initial begin
        // Not needed on Cloud V:
        $dumpfile("tb_barrett_reduction.vcd"); // Name of the signal dump file
        $dumpvars(0, tb_barrett_reduction); // Signals to dump
    end

endmodule

rtl/bu/tb_barrett_reduction.vcd
$date
	Thu Aug 24 17:08:52 2023
$end
$version
	Icarus Verilog
$end
$timescale
	1ps
$end
$scope module tb_barrett_reduction $end
$var wire 16 ! result [15:0] $end
$var reg 32 " c [31:0] $end
$var reg 32 # expected_result [31:0] $end
$var integer 32 $ input_file [31:0] $end
$var integer 32 % output_file [31:0] $end
$scope module uut $end
$var wire 32 & c [31:0] $end
$var wire 16 ' result_temp [15:0] $end
$var wire 16 ( result [15:0] $end
$var wire 32 ) floor_c_mu_q [31:0] $end
$var wire 32 * c_mu_l [31:0] $end
$var wire 64 + c_mu [63:0] $end
$var parameter 32 , mu $end
$var parameter 16 - q $end
$upscope $end
$scope begin $ivl_for_loop0 $end
$var integer 32 . i [31:0] $end
$upscope $end
$upscope $end
$enddefinitions $end
$comment Show the parameter values. $end
$dumpall
b110100000001 -
b100111010111110110111 ,
$end
#0
$dumpvars
b0 .
b1011000111111110001011110001010001001100010111100 +
b10110001111111100 *
b10010000101010010111111111100 )
b10100101000 (
b10100101000 '
b10010000101010011010100100100 &
b10000000000000000000000000000100 %
b10000000000000000000000000000011 $
bx #
b10010000101010011010100100100 "
b10100101000 !
$end
#10
b101100101000 !
b101100101000 (
b11000000100010010101001101011001 )
b11101100111001011001 *
b101100101000 '
b1110110011100101100110001101010111111011110100110111 +
b11000000100010010101111010000001 "
b11000000100010010101111010000001 &
b1 .
b10100101000 #
#20
b100000111000 !
b100000111000 (
b10000100100001001100110111010001 )
b10100011000011010001 *
b100000111000 '
b1010001100001101000101101011111100000010011101101111 +
b10000100100001001101011000001001 "
b10000100100001001101011000001001 &
b10 .
b101100101000 #
#30
b1001101010 !
b1001101010 (
b10110001111100000100011011111000 )
b11011010111011111000 *
b111101101011 '
b1101101011101111100011100111001101000110110111000101 +
b10110001111100000101011001100011 "
b10110001111100000101011001100011 &
b11 .
b100000111000 #
#40
b100110101100 !
b100110101100 (
b110101110010111000101100001 )
b1000010001100001 *
b100110101100 '
b100001000110000110111011101010111101100101001011 +
b110101110010111101100001101 "
b110101110010111101100001101 &
b100 .
b1001101010 #
#50
b1001111 !
b1001111 (
b1000110110111111000110000111101 )
b1010111001100111101 *
b110101010000 '
b101011100110011110111101001010001010010011011001011 +
b1000110110111111001100110001101 "
b1000110110111111001100110001101 &
b101 .
b100110101100 #
#60
b101101000011 !
b101101000011 (
b10110010110000100111100100100010 )
b11011011111100100010 *
b101101000011 '
b1101101111110010001010010101000011001010111100110011 +
b10110010110000101000010001100101 "
b10110010110000101000010001100101 &
b110 .
b1001111 #
#70
b1011001000 !
b1011001000 (
b10001001001101110100001001001001 )
b10101000110101001001 *
b111111001001 '
b1010100011010100100111111110111110111111100011011110 +
b10001001001101110101001000010010 "
b10001001001101110101001000010010 &
b111 .
b101101000011 #
#80
b1101000000 !
b1101000000 (
b111100111101111111000001 )
b1001011000001 *
b1101000000 '
b100101100000100111111100101111111010010110111 +
b111100111110001100000001 "
b111100111110001100000001 &
b1000 .
b1011001000 #
#90
b100001010111 !
b100001010111 (
b110110101111100010010110110 )
b1000011010110110 *
b100001010111 '
b100001101011011010100001011001100111011101001011 +
b110110101111100110100001101 "
b110110101111100110100001101 &
b1001 .
b1101000000 #
#100
b101100110100 !
b101100110100 (
b111011001000111110011001000010 )
b1001000110001000010 *
b101100110100 '
b100100011000100001011000100100000110100010101011010 +
b111011001000111111000101110110 "
b111011001000111111000101110110 &
b1010 .
b100001010111 #
#110
b10111110 !
b10111110 (
b11110100011011100110001111111 )
b100101100101111111 *
b10111110 '
b10010110010111111100000010001100010110100110011011 +
b11110100011011100110100111101 "
b11110100011011100110100111101 &
b1011 .
b101100110100 #
#120
b101010011011 !
b101010011011 (
b1110110110101000100110101010010 )
b10010010001101010010 *
b101010011011 '
b1001001000110101001010100000011111001101110101101011 +
b1110110110101000101011111101101 "
b1110110110101000101011111101101 &
b1100 .
b10111110 #
#130
b11110111 !
b11110111 (
b1000110001011011110100110010100 )
b1010110010110010100 *
b110111111000 '
b101011001011001010011110110011110001010100100010100 +
b1000110001011011111011110001100 "
b1000110001011011111011110001100 &
b1101 .
b101010011011 #
#140
b11001010110 !
b11001010110 (
b1111100111111011110001110100011 )
b10011001110010100011 *
b11001010110 '
b1001100111001010001101001001111011100111011111111111 +
b1111100111111011110100111111001 "
b1111100111111011110100111111001 &
b1110 .
b11110111 #
#150
b1010111001 !
b1010111001 (
b11100011001101110001010100001100 )
b100010111100100001100 *
b111110111010 '
b10001011110010000110011011001010000001010001110001010 +
b11100011001101110010010011000110 "
b11100011001101110010010011000110 &
b1111 .
b11001010110 #
#160
b100010011101 !
b100010011101 (
b11100010111101110111110000101000 )
b100010111010000101000 *
b100010011101 '
b10001011101000010100001001101010100011001001111010011 +
b11100010111101111000010011000101 "
b11100010111101111000010011000101 &
b10000 .
b1010111001 #
#170
b101011110001 !
b101011110001 (
b11010101000100111100011110111001 )
b100000110001010111001 *
b101011110001 '
b10000011000101011100110000000110010111100110110000110 +
b11010101000100111101001010101010 "
b11010101000100111101001010101010 &
b10001 .
b100010011101 #
#180
b101100011110 !
b101100011110 (
b1110010101011111110110011000111 )
b10001101000111000111 *
b101100011110 '
b1000110100011100011110101100001111101011111110110011 +
b1110010101011111111011111100101 "
b1110010101011111111011111100101 &
b10010 .
b101011110001 #
#190
b101111101110 !
b101111101110 (
b10111011110100100110011010001001 )
b11100111000110001001 *
b101111101110 '
b1110011100011000100110011110100001000010110000010001 +
b10111011110100100111001001110111 "
b10111011110100100111001001110111 &
b10011 .
b101100011110 #
#200
b110000100001 !
b110000100001 (
b10001001001100101100100111110001 )
b10101000110011110001 *
b110000100001 '
b1010100011001111000110110111000000110101010011011110 +
b10001001001100101101011000010010 "
b10001001001100101101011000010010 &
b10100 .
b101111101110 #
#210
b100110011101 !
b100110011101 (
b1000111111011001101000111110010 )
b1011000011111110010 *
b100110011101 '
b101100001111111001010100000000001001011010000111001 +
b1000111111011001101101110001111 "
b1000111111011001101101110001111 &
b10101 .
b110000100001 #
#220
b101000101100 !
b101000101100 (
b1111001001100000101111111000110 )
b10010101000111000110 *
b101000101100 '
b1001010100011100011010010110111111100010100111111110 +
b1111001001100000110100111110010 "
b1111001001100000110100111110010 &
b10110 .
b100110011101 #
#230
b100100001 !
b100100001 (
b11100111011101101000100010101100 )
b100011100110010101100 *
b111000100010 '
b10001110011001010110010111000001001101001111101000010 +
b11100111011101101001011011001110 "
b11100111011101101001011011001110 &
b10111 .
b101000101100 #
#240
b1101100100 !
b1101100100 (
b11110100000000000110101010000011 )
b100101100001110000011 *
b1000001100101 '
b10010110000111000001111011111100101000111001111011000 +
b11110100000000000111101011101000 "
b11110100000000000111101011101000 &
b11000 .
b100100001 #
#250
b100000010111 !
b100000010111 (
b11100010110010100100011010101110 )
b100010111000010101110 *
b100000010111 '
b10001011100001010111001000011000101011111100111010011 +
b11100010110010100100111011000101 "
b11100010110010100100111011000101 &
b11001 .
b1101100100 #
#260
b110100000000 !
b110100000000 (
b101110010110000011110001011100 )
b111001000001011100 *
b110100000000 '
b11100100000101110011101101000101100101010011000100 +
b101110010110000100100101011100 "
b101110010110000100100101011100 &
b11010 .
b100000010111 #
#270
b100001101110 !
b100001101110 (
b11011110100011100010000001001111 )
b100010001110101001111 *
b100001101110 '
b10001000111010100111101001011011111110101001000011011 +
b11011110100011100010100010111101 "
b11011110100011100010100010111101 &
b11011 .
b110100000000 #
#280
b100000001011 !
b100000001011 (
b10010110101010110101000000100010 )
b10111001011000100010 *
b100000001011 '
b1011100101100010001001100001000110011100101100101011 +
b10010110101010110101100000101101 "
b10010110101010110101100000101101 &
b11100 .
b100001101110 #
#290
b101011101 !
b101011101 (
b10110010101001110001100000000111 )
b11011011110100000111 *
b111001011110 '
b1101101111010000011111010010001110100111110100110011 +
b10110010101001110010011001100101 "
b10110010101001110010011001100101 &
b11101 .
b100000001011 #
#300
b10101111101 !
b10101111101 (
b10110001111011110101110011100110 )
b11011010111011100110 *
b10101111101 '
b1101101011101110011000100011101110100000000111000101 +
b10110001111011110110001001100011 "
b10110001111011110110001001100011 &
b11110 .
b101011101 #
#310
b101110111010 !
b101110111010 (
b101011100110111101101010000 )
b110101101010000 *
b101110111010 '
b11010110101000011100100101000110101111000100110 +
b101011100111000011100001010 "
b101011100111000011100001010 &
b11111 .
b10101111101 #
#320
b100100101011 !
b100100101011 (
b11000000001110110001100101010101 )
b11101100100001010101 *
b100100101011 '
b1110110010000101010101100110010110110010100110000000 +
b11000000001110110010001010000000 "
b11000000001110110010001010000000 &
b100000 .
b101110111010 #
#330
b100001110010 !
b100001110010 (
b10000011001000001100010101110 )
b10100001010101110 *
b100001110010 '
b1010000101010111010011111100110001000110111100000 +
b10000011001000010000100100000 "
b10000011001000010000100100000 &
b100001 .
b100100101011 #
#340
b100000010011 !
b100000010011 (
b1010101011110000011110110010111 )
b1101001001010010111 *
b100000010011 '
b110100100101001011101111100001101110000001010000110 +
b1010101011110000100010110101010 "
b1010101011110000100010110101010 &
b100010 .
b100001110010 #
#350
b10001111000 !
b10001111000 (
b11001110110011001100100000100101 )
b11111110011100100101 *
b10001111000 '
b1111111001110010010100000011111011001001011100111011 +
b11001110110011001100110010011101 "
b11001110110011001100110010011101 &
b100011 .
b100000010011 #
#360
b1011000101 !
b1011000101 (
b11001011001000000010111011010000 )
b11111001111011010000 *
b111111000110 '
b1111100111101101000011100011111101110100011100111010 +
b11001011001000000011111010010110 "
b11001011001000000011111010010110 &
b100100 .
b10001111000 #
#370
b1011101001 !
b1011101001 (
b10001001100000111011010100101010 )
b10101001001100101010 *
b1011101001 '
b1010100100110010101000000001011001101001001010010101 +
b10001001100000111011100000010011 "
b10001001100000111011100000010011 &
b100101 .
b1011000101 #
#380
b10010011010 !
b10010011010 (
b10000110101111000011001101110011 )
b10100101110001110011 *
b10010011010 '
b1010010111000111001100100011110100111111010001001011 +
b10000110101111000011100000001101 "
b10000110101111000011100000001101 &
b100110 .
b1011101001 #
#390
b1001101011 !
b1001101011 (
b10101001101001111100011011100111 )
b11010000101111100111 *
b111101101100 '
b1101000010111110011111101010101001011111001001010101 +
b10101001101001111101011001010011 "
b10101001101001111101011001010011 &
b100111 .
b10010011010 #
#400
b110111111 !
b110111111 (
b110101100111111101101110101100 )
b1000001111110101100 *
b110111111 '
b100000111111010110000001100100101000110110001111101 +
b110101100111111101110101101011 "
b110101100111111101110101101011 &
b101000 .
b1001101011 #
#410
b101101110001 !
b101101110001 (
b11101010101001100001111101100100 )
b100100000101101100100 *
b101101110001 '
b10010000010110110010010000001110111110011100101000011 +
b11101010101001100010101011010101 "
b11101010101001100010101011010101 &
b101001 .
b110111111 #
#420
b101110101101 !
b101110101101 (
b10000001000101110011111001010101 )
b10011110110101010101 *
b101110101101 '
b1001111011010101010110110001011000110100010101101110 +
b10000001000101110100101000000010 "
b10000001000101110100101000000010 &
b101010 .
b101101110001 #
#430
b101101111010 !
b101101111010 (
b11010111010101100011001100110100 )
b100001000111100110100 *
b101101111010 '
b10000100011110011010010001010011010011100000001100010 +
b11010111010101100011111010101110 "
b11010111010101100011111010101110 &
b101011 .
b101110101101 #
#440
b110011010100 !
b110011010100 (
b1110111111111101110001001001 )
b10010011101001001 *
b110011010100 '
b1001001110100100111110110011100010111011010111011 +
b1110111111111110100100011101 "
b1110111111111110100100011101 &
b101100 .
b101101111010 #
#450
b11100010010 !
b11100010010 (
b11100111110001010110101110111101 )
b100011101001010111101 *
b11100010010 '
b10001110100101011110100101100111111011001001011111001 +
b11100111110001010111001011001111 "
b11100111110001010111001011001111 &
b101101 .
b110011010100 #
#460
b10101001100 !
b10101001100 (
b10001100001000100001111010111 )
b10101100011010111 *
b10101001100 '
b1010110001101011101100001001010000011010100000101 +
b10001100001000100100100100011 "
b10001100001000100100100100011 &
b101110 .
b11100010010 #
#470
b11011100011 !
b11011100011 (
b101000010010101111000100111 )
b110001100100111 *
b11011100011 '
b11000110010011110000101100001110001000000100110 +
b101000010010110010100001010 "
b101000010010110010100001010 &
b101111 .
b10101001100 #
#480
b101011000011 !
b101011000011 (
b11100101011100110000000000000111 )
b100011010010100000111 *
b101011000011 '
b10001101001010000011101110110100110101100110001100110 +
b11100101011100110000101011001010 "
b11100101011100110000101011001010 &
b110000 .
b11011100011 #
#490
b100011111111 !
b100011111111 (
b10011110001100010100001100111101 )
b11000010101000111101 *
b100011111111 '
b1100001010100011110101110000110011101000001011100100 +
b10011110001100010100110000111100 "
b10011110001100010100110000111100 &
b110001 .
b101011000011 #
#500
b100011010111 !
b100011010111 (
b1111001011010001011010100011011 )
b10010101011000011011 *
b100011010111 '
b1001010101100001101101111100101011100011010111111110 +
b1111001011010001011110111110010 "
b1111001011010001011110111110010 &
b110010 .
b100011111111 #
#510
b11010011101 !
b11010011101 (
b1000101001011100101101011101101 )
b1010101000111101101 *
b11010011101 '
b101010100011110110101100110000100110000111110100110 +
b1000101001011100110000110001010 "
b1000101001011100110000110001010 &
b110011 .
b100011010111 #
#520
b1100101010 !
b1100101010 (
b100000110001001011000000010111 )
b101000010100010111 *
b1100101010 '
b10100001010001011100110000111110001001001001110111 +
b100000110001001011001101000001 "
b100000110001001011001101000001 &
b110100 .
b11010011101 #
#530
b100000010011 !
b100000010011 (
b11101100010010110010110011000101 )
b100100010101111000101 *
b100000010011 '
b10010001010111100010100111110111010100110111001101000 +
b11101100010010110011010011011000 "
b11101100010010110011010011011000 &
b110101 .
b1100101010 #
#540
b100011000001 !
b100011000001 (
b111100001000001110101010110111 )
b1001001111110110111 *
b100011000001 '
b100100111111011011110010011111001010001001011001000 +
b111100001000001111001101111000 "
b111100001000001111001101111000 &
b110110 .
b100000010011 #
#550
b11101100011 !
b11101100011 (
b11000100100010100000101100100110 )
b11110001110100100110 *
b11101100011 '
b1111000111010010011001000001100010011110011011101111 +
b11000100100010100001001010001001 "
b11000100100010100001001010001001 &
b110111 .
b100011000001 #
#560
b101110101 !
b101110101 (
b1110101110001001111111101110101 )
b10010000111001110101 *
b111001110110 '
b1001000011100111010111101100110100011001011111111101 +
b1110101110001010000110111101011 "
b1110101110001010000110111101011 &
b111000 .
b11101100011 #
#570
b10100010001 !
b10100010001 (
b1011011000000100110000010100101 )
b1101111111110100101 *
b10100010001 '
b110111111111010010100111110110000000001111100011010 +
b1011011000000100110010110110110 "
b1011011000000100110010110110110 &
b111001 .
b101110101 #
#580
b11111111011 !
b11111111011 (
b1100011010010111111000111001011 )
b1111010001011001011 *
b11111111011 '
b111101000101100101101110100101111111110011010001010 +
b1100011010010111111100111000110 "
b1100011010010111111100111000110 &
b111010 .
b10100010001 #
#590
b1101011000 !
b1101011000 (
b1010111000101010001000001010110 )
b1101011001001010110 *
b1101011000 '
b110101100100101011000011110011011110000001101100010 +
b1010111000101010001001110101110 "
b1010111000101010001001110101110 &
b111011 .
b11111111011 #
#600
b11101011100 !
b11101011100 (
b11011110011101001111101101100000 )
b100010001101101100000 *
b11101011100 '
b10001000110110110000000110110011101110111100001100100 +
b11011110011101010000001010111100 "
b11011110011101010000001010111100 &
b111100 .
b1101011000 #
#610
b10010001000 !
b10010001000 (
b10101000011111101100010100010 )
b11001111010100010 *
b10010001000 '
b1100111101010001001010000101001001100111100000110 +
b10101000011111101110100101010 "
b10101000011111101110100101010 &
b111101 .
b11101011100 #
#620
b100100101101 !
b100100101101 (
b10000101110101111001000011011110 )
b10100100101011011110 *
b100100101101 '
b1010010010101101111001111110001111011010001011011101 +
b10000101110101111001101000001011 "
b10000101110101111001101000001011 &
b111110 .
b10010001000 #
#630
b101111010 !
b101111010 (
b10111000100101111010111111110110 )
b11100011000111110110 *
b111001111011 '
b1110001100011111011011010010000010110110000111000111 +
b10111000100101111011111001110001 "
b10111000100101111011111001110001 &
b111111 .
b100100101101 #
#640
b10110010111 !
b10110010111 (
b1000010111100100011101111101110 )
b1010010010111101110 *
b10110010111 '
b101001001011110111001010010110101011100000100010011 +
b1000010111100100100000110000101 "
b1000010111100100100000110000101 &
b1000000 .
b101111010 #
#650
b11111101000 !
b11111101000 (
b100111111100100100110101100111 )
b110001001001100111 *
b11111101000 '
b11000100100110011110001011011010001111110001111001 +
b100111111100100101010101001111 "
b100111111100100101010101001111 &
b1000001 .
b10110010111 #
#660
b101111000001 !
b101111000001 (
b10011101110011000101010001111010 )
b11000010001001111010 *
b101111000001 '
b1100001000100111101010100111010000100001111100101101 +
b10011101110011000110000000111011 "
b10011101110011000110000000111011 &
b1000010 .
b11111101000 #
#670
b101011011001 !
b101011011001 (
b11101000001100010100001100001 )
b100011101101100001 *
b101011011001 '
b10001110110110000111001001110000010100010001110110 +
b11101000001100011001100111010 "
b11101000001100011001100111010 &
b1000011 .
b101111000001 #
#680
b100110110000 !
b100110110000 (
b10111111001000110010100011001110 )
b11101011001011001110 *
b100110110000 '
b1110101100101100111001110001000001110011101000010010 +
b10111111001000110011001001111110 "
b10111111001000110011001001111110 &
b1000100 .
b101011011001 #
#690
b100000100000 !
b100000100000 (
b1010101010100100001011110101 )
b1101000111110101 *
b100000100000 '
b110100011111010110011011100111100000011100000011 +
b1010101010100100101100010101 "
b1010101010100100101100010101 &
b1000101 .
b100110110000 #
#700
b101111011000 !
b101111011000 (
b1111000110110011001000000011001 )
b10010100101100011001 *
b101111011000 '
b1001010010110001100110111000000010110011100001000111 +
b1111000110110011001101111110001 "
b1111000110110011001101111110001 &
b1000110 .
b100000100000 #
#710
b1110110011 !
b1110110011 (
b1101100100111000100100000100110 )
b10000101101000100110 *
b1110110011 '
b1000010110100010011000011100101011101000111100011111 +
b1101100100111000100101111011001 "
b1101100100111000100101111011001 &
b1000111 .
b101111011000 #
#720
b100100001111 !
b100100001111 (
b110001001000101111111001010011 )
b111100011101010011 *
b100100001111 '
b11110001110101001110011110010111000100010100001110 +
b110001001000110000011101100010 "
b110001001000110000011101100010 &
b1001000 .
b1110110011 #
#730
b110000010001 !
b110000010001 (
b100110001101011110111100111011 )
b101111000000111011 *
b110000010001 '
b10111100000011101111011110000000111001011101010100 +
b100110001101011111101101001100 "
b100110001101011111101101001100 &
b1001001 .
b100100001111 #
#740
b100011111110 !
b100011111110 (
b1001111101000010100110010100001 )
b1100001111110100001 *
b100011111110 '
b110000111111010000110010000101010001110010110101001 +
b1001111101000010101010110011111 "
b1001111101000010101010110011111 &
b1001010 .
b110000010001 #
#750
b1110001101 !
b1110001101 (
b1000111101110011001111000000010 )
b1011000010000000010 *
b1110001101 '
b101100001000000001000101000110000000011111000111001 +
b1000111101110011010000110001111 "
b1000111101110011010000110001111 &
b1001011 .
b100011111110 #
#760
b100101101101 !
b100101101101 (
b1111100011011011010000010001011 )
b10011001000110001011 *
b100101101101 '
b1001100100011000101110000110111111010000100001001000 +
b1111100011011011010100111111000 "
b1111100011011011010100111111000 &
b1001100 .
b1110001101 #
#770
b10011010 !
b10011010 (
b11011011110011010101001100011100 )
b100001110011100011100 *
b110110011011 '
b10000111001110001110010110010100000100011101111010001 +
b11011011110011010110000010110111 "
b11011011110011010110000010110111 &
b1001101 .
b100101101101 #
#780
b11001110001 !
b11001110001 (
b11001111110001000101000000101110 )
b11111111101000101110 *
b11001110001 '
b1111111110100010111000101010010111011001110010101001 +
b11001111110001000101011010011111 "
b11001111110001000101011010011111 &
b1001110 .
b10011010 #
#790
b101101000110 !
b101101000110 (
b10101110011111011000100100010110 )
b11010110101100010110 *
b101101000110 '
b1101011010110001011010010111000000111111000111000100 +
b10101110011111011001010001011100 "
b10101110011111011001010001011100 &
b1001111 .
b11001110001 #
#800
b11110001 !
b11110001 (
b10101101110010111011001001101001 )
b11010101110101101001 *
b110111110010 '
b1101010111010110100111001011111001011011011000001101 +
b10101101110010111100000001011011 "
b10101101110010111100000001011011 &
b1010000 .
b101101000110 #
#810
b10011000110 !
b10011000110 (
b1000100110111100011001011000011 )
b1010100101111000011 *
b10011000110 '
b101010010111100001101000001111110110101100111101111 +
b1000100110111100011011110001001 "
b1000100110111100011011110001001 &
b1010001 .
b11110001 #
#820
b101001010011 !
b101001010011 (
b10100100101011100010011111110110 )
b11001010100111110110 *
b101001010011 '
b1100101010011111011010001000010100001101100100101111 +
b10100100101011100011001001001001 "
b10100100101011100011001001001001 &
b1010010 .
b10011000110 #
#830
b11011100 !
b11011100 (
b11101000001000110011000011110011 )
b100011101100111110011 *
b110111011101 '
b10001110110011111001110110010100100100001011010110000 +
b11101000001000110011111011010000 "
b11101000001000110011111011010000 &
b1010011 .
b101001010011 #
#840
b11011110011 !
b11011110011 (
b11101011111111101011100111100100 )
b100100010010111100100 *
b11011110011 '
b10010001001011110010000101000111000111101001010110001 +
b11101011111111101100000011010111 "
b11101011111111101100000011010111 &
b1010100 .
b11011100 #
#850
b10010100000 !
b10010100000 (
b10101000110001111111011110110001 )
b11001111101010110001 *
b10010100000 '
b1100111110101011000100010110011100111011110011100111 +
b10101000110001111111110001010001 "
b10101000110001111111110001010001 &
b1010101 .
b11011110011 #
#860
b10001110 !
b10001110 (
b1001011001000010010001000000111 )
b1011100011100000111 *
b110110001111 '
b101110001110000011111101100011000101000111000111010 +
b1001011001000010010111110010110 "
b1001011001000010010111110010110 &
b1010110 .
b10010100000 #
#870
b110010101010 !
b110010101010 (
b110000111010111001001100010 )
b111100001100010 *
b110010101010 '
b11110000110001011110110110100110000010110010100 +
b110000111010111111100001100 "
b110000111010111111100001100 &
b1010111 .
b10001110 #
#880
b1111100000 !
b1111100000 (
b11100001001011001011110111100001 )
b100010101000011100001 *
b1000011100001 '
b10001010100001110000111110000110001000110101010101110 +
b11100001001011001100111011000010 "
b11100001001011001100111011000010 &
b1011000 .
b110010101010 #
#890
b100001100010 !
b100001100010 (
b1100100010101111110010101100110 )
b1111011011101100110 *
b100001100010 '
b111101101110110011001111100001111101011000111111000 +
b1100100010101111110110111001000 "
b1100100010101111110110111001000 &
b1011001 .
b1111100000 #
#900
b1000010110 !
b1000010110 (
b10111011100000100100101101100000 )
b11100110101101100000 *
b111100010111 '
b1110011010110110000011011100110110110000010000010001 +
b10111011100000100101101001110111 "
b10111011100000100101101001110111 &
b1011010 .
b100001100010 #
#910
b101011111000 !
b101011111000 (
b11110111100101110001001000101 )
b100110000101000101 *
b101011111000 '
b10011000010100010111001011010110110100100110011011 +
b11110111100101110110100111101 "
b11110111100101110110100111101 &
b1011011 .
b1000010110 #
#920
b11011101000 !
b11011101000 (
b1001000011001101010000101010 )
b1011001000101010 *
b11011101000 '
b101100100010101010000100010001111110011111011110 +
b1001000011001101101100010010 "
b1001000011001101101100010010 &
b1011100 .
b101011111000 #
#930
b10000000010 !
b10000000010 (
b10111111000001001111110001111100 )
b11101011000001111100 *
b10000000010 '
b1110101100000111110000000001010000110111110000010010 +
b10111111000001010000000001111110 "
b10111111000001010000000001111110 &
b1011101 .
b11011101000 #
#940
b101010110111 !
b101010110111 (
b110110111001010111011010110110 )
b1000011100010110110 *
b101010110111 '
b100001110001011011010111100101000000000011111101011 +
b110110111001011000000101101101 "
b110110111001011000000101101101 &
b1011110 .
b10000000010 #
#950
b101001000000 !
b101001000000 (
b11100110110011101110011111001 )
b100011011111111001 *
b101001000000 '
b10001101111111100110111110000011110100000010111111 +
b11100110110011110011100111001 "
b11100110110011110011100111001 &
b1011111 .
b101010110111 #
#960
b101110100011 !
b101110100011 (
b1111110100101000001101111100 )
b10011011101111100 *
b101110100011 '
b1001101110111110011011110101001111000000000101001 +
b1111110100101000111100011111 "
b1111110100101000111100011111 &
b1100000 .
b101001000000 #
#970
b1011000000 !
b1011000000 (
b11101001111010111110011100010010 )
b100011111110100010010 *
b111111000001 '
b10001111111010001001011010111000100001010110111010101 +
b11101001111010111111011011010011 "
b11101001111010111111011011010011 &
b1100001 .
b101110100011 #
#980
b101110000101 !
b101110000101 (
b1000010110110010010010000000000 )
b1010010010000000000 *
b101110000101 '
b101001001000000000011000111100110111110001100010011 +
b1000010110110010010111110000101 "
b1000010110110010010111110000101 &
b1100010 .
b1011000000 #
#990
b101111011010 !
b101111011010 (
b10111100000101000111110010011110 )
b11100111011010011110 *
b101111011010 '
b1110011101101001111010011100110111111001010111001000 +
b10111100000101001000100001111000 "
b10111100000101001000100001111000 &
b1100011 .
b101110000101 #
#1000
b100110101110 !
b100110101110 (
b101101110110100100111110101101 )
b111000011010101101 *
b100110101110 '
b11100001101010110110101011111011000001010100001101 +
b101101110110100101100101011011 "
b101101110110100101100101011011 &
b1100100 .
b101111011010 #
#1010
b110011011110 !
b110011011110 (
b100100100010110011111001101011 )
b101100111101101011 *
b110011011110 '
b10110011110110101111101110011101001011100000101111 +
b100100100010110100101101001001 "
b100100100010110100101101001001 &
b1100101 .
b100110101110 #
#1020
b10101110011 !
b10101110011 (
b10011111111100101010100011001100 )
b11000100110011001100 *
b10101110011 '
b1100010011001100110000101010010001001010000000001001 +
b10011111111100101010111000111111 "
b10011111111100101010111000111111 &
b1100110 .
b110011011110 #
#1030
b100111000111 !
b100111000111 (
b10101000011001010010101100011 )
b11001111001100011 *
b100111000111 '
b1100111100110001110110111111011001110110100000110 +
b10101000011001010111100101010 "
b10101000011001010111100101010 &
b1100111 .
b10101110011 #
#1040
b11110000000 !
b11110000000 (
b101100000101010101101111011000 )
b110110001111011000 *
b11110000000 '
b11011000111101100010000001101110110010101111101000 +
b101100000101010110001101011000 "
b101100000101010110001101011000 &
b1101000 .
b100111000111 #
#1050
b1111010001 !
b1111010001 (
b11000011001111110010011110110100 )
b11110000001110110100 *
b1000011010010 '
b1111000000111011010011111011110001110000000111001010 +
b11000011001111110011100010000110 "
b11000011001111110011100010000110 &
b1101001 .
b11110000000 #
#1060
b10011110110 !
b10011110110 (
b11000111000110100000011110011000 )
b11110100111110011000 *
b10011110110 '
b1111010011111001100000010000101111100000101110000010 +
b11000111000110100000110010001110 "
b11000111000110100000110010001110 &
b1101010 .
b1111010001 #
#1070
b11010000111 !
b11010000111 (
b11001110001011111110110000010101 )
b11111101101100010101 *
b11010000111 '
b1111110110110001010100101100101100110001000110000100 +
b11001110001011111111001010011100 "
b11001110001011111111001010011100 &
b1101011 .
b10011110110 #
#1080
b101000001111 !
b101000001111 (
b1111101001101011000111111101011 )
b10011010000011101011 *
b101000001111 '
b1001101000001110101110010011001000001111011110110110 +
b1111101001101011001100111111010 "
b1111101001101011001100111111010 &
b1101100 .
b11010000111 #
#1090
b11110010101 !
b11110010101 (
b10010011011111011011010010010001 )
b10110101011110010001 *
b11110010101 '
b1011010101111001000101011001010100010111100100101010 +
b10010011011111011011110000100110 "
b10010011011111011011110000100110 &
b1101101 .
b101000001111 #
#1100
b11111001001 !
b11111001001 (
b111001100101100000111110101010 )
b1000110110110101010 *
b11111001001 '
b100011011011010101010000001110110110110000000110101 +
b111001100101100001011101110011 "
b111001100101100001011101110011 &
b1101110 .
b11110010101 #
#1110
b1110000 !
b1110000 (
b11010001100010111010011100110010 )
b100000001110100110010 *
b110101110001 '
b10000000111010011001010110011011100101000110110000101 +
b11010001100010111011010010100011 "
b11010001100010111011010010100011 &
b1101111 .
b11111001001 #
#1120
b110111001 !
b110111001 (
b10010111100110011001100101110101 )
b10111010100001110101 *
b111010111010 '
b1011101010000111010111100100010011000101101010011001 +
b10010111100110011010100000101111 "
b10010111100110011010100000101111 &
b1110000 .
b1110000 #
#1130
b101110010000 !
b101110010000 (
b11011001110100101000011100100011 )
b100001100000000100011 *
b101110010000 '
b10000110000000010001110001011000110000011101011110101 +
b11011001110100101001001010110011 "
b11011001110100101001001010110011 &
b1110001 .
b110111001 #
